{
	"id": "672cbfd3-e567-473c-8d6c-3220ad9ea02b",
	"name": "Kiosk_UAT_API_Environment_Collection Copy",
	"values": [
		{
			"key": "BaseURL",
			"value": "https://api-dev.bankone.mu:8243/MW/api/MW/",
			"enabled": true
		},
		{
			"key": "clientID",
			"value": "DFBE1557-DEA5-4BB7-8C60-7E48501768F2",
			"enabled": true
		},
		{
			"key": "EncReq",
			"value": "",
			"enabled": true
		},
		{
			"key": "EncRes",
			"value": "",
			"enabled": true
		},
		{
			"key": "ReqRefId",
			"value": "",
			"enabled": true
		},
		{
			"key": "popReqId",
			"value": "",
			"enabled": true
		}
	],
	"_postman_variable_scope": "environment",
	"_postman_exported_at": "2023-07-20T07:52:30.525Z",
	"_postman_exported_using": "Postman/10.15.8"
}